sparsejac/__init__.py
sparsejac/sparsejac.py
sparsejac-0.2.0.dist-info/LICENSE
sparsejac-0.2.0.dist-info/METADATA
sparsejac-0.2.0.dist-info/WHEEL
sparsejac-0.2.0.dist-info/top_level.txt
sparsejac-0.2.0.dist-info/RECORD
