Metadata-Version: 2.1
Name: sparsejac
Version: 0.2.0
Summary: Efficient forward- and reverse-mode sparse Jacobians using Jax.
Author-email: Martin Schubert <mfschubert@gmail.com>
Maintainer-email: Martin Schubert <mfschubert@gmail.com>
License: MIT License
Keywords: jax,jacobian,sparse
Requires-Python: >=3.7
License-File: LICENSE
Requires-Dist: jax
Requires-Dist: jaxlib
Requires-Dist: networkx
Requires-Dist: numpy
Requires-Dist: scipy
Provides-Extra: tests
Requires-Dist: parameterized; extra == "tests"
Requires-Dist: pytest; extra == "tests"
Requires-Dist: pytest-cov; extra == "tests"
Provides-Extra: dev
Requires-Dist: bump-my-version; extra == "dev"
Requires-Dist: darglint; extra == "dev"
Requires-Dist: sparsejac[tests]; extra == "dev"
Requires-Dist: pre-commit; extra == "dev"
